radixhopper/__about__.py
radixhopper/__init__.py
radixhopper/cli.py
radixhopper/error.py
radixhopper/radixhopper.py
radixhopper/tooling.py
radixhopper-1.0.0.dist-info/METADATA
radixhopper-1.0.0.dist-info/WHEEL
radixhopper-1.0.0.dist-info/entry_points.txt
radixhopper-1.0.0.dist-info/licenses/LICENSE
radixhopper-1.0.0.dist-info/RECORD
