Metadata-Version: 2.4
Name: radixhopper
Version: 1.0.0
Summary: A Python library for efficient radix-based number system conversions, specializing in cyclic fractions handling, for bases 2 through 36.
Project-URL: Documentation, https://github.com/aarmn/radixhopper#readme
Project-URL: Issues, https://github.com/aarmn/radixhopper/issues
Project-URL: Source, https://github.com/aarmn/radixhopper
Author-email: aarmn <aarmn80@gmail.com>
License: MIT License
License-File: LICENSE
Keywords: bases,conversion,cyclic fractions,math,mathematics,number system,radix
Classifier: Development Status :: 4 - Beta
Classifier: Programming Language :: Python
Classifier: Programming Language :: Python :: 3.8
Classifier: Programming Language :: Python :: 3.9
Classifier: Programming Language :: Python :: 3.10
Classifier: Programming Language :: Python :: 3.11
Classifier: Programming Language :: Python :: 3.12
Classifier: Programming Language :: Python :: 3.13
Classifier: Programming Language :: Python :: Implementation :: CPython
Classifier: Programming Language :: Python :: Implementation :: PyPy
Requires-Python: >=3.8
Requires-Dist: typeguard>=4.4.0
Requires-Dist: typer>=0.15.2
Provides-Extra: cli
Requires-Dist: fire>=0.4.0; extra == 'cli'
Requires-Dist: rich; extra == 'cli'
Provides-Extra: dev
Requires-Dist: hatch; extra == 'dev'
Requires-Dist: pytest; extra == 'dev'
Requires-Dist: pytest-cov; extra == 'dev'
Requires-Dist: ruff; extra == 'dev'
Requires-Dist: uv; extra == 'dev'
